Metadata-Version: 1.0
Name: vcscraping
Version: 1.0.3
Summary: vcscraping by Viniette & Clarity.
Home-page: UNKNOWN
Author: Shoya Yasuda @ Viniette & Clarity, Inc.
Author-email: selamatpagi1124@gmail.com
License: Required: Copyright notice in any social outputs.     Permitted: Private Use, Commercial Use.     Forbidden: Sublicense, Modifications, Distribution, Patent Grant, Use Trademark, Hold Liable.
Platform: UNKNOWN
